mcp_server_ipinfo/__init__.py
mcp_server_ipinfo/cache.py
mcp_server_ipinfo/ipinfo.py
mcp_server_ipinfo/models.py
mcp_server_ipinfo/server.py
mcp_server_ipinfo-0.2.0.dist-info/METADATA
mcp_server_ipinfo-0.2.0.dist-info/WHEEL
mcp_server_ipinfo-0.2.0.dist-info/entry_points.txt
mcp_server_ipinfo-0.2.0.dist-info/licenses/LICENSE
mcp_server_ipinfo-0.2.0.dist-info/RECORD
