Metadata-Version: 2.4
Name: mcp-server-ipinfo
Version: 0.2.0
Summary: IP Geolocation Server for MCP
Project-URL: Repository, https://github.com/briandconnelly/mcp-server-ipinfo.git
Project-URL: Issues, https://github.com/briandconnelly/mcp-server-ipinfo/issues
Author-email: Brian Connelly <bdc@bconnelly.net>
License: MIT License
License-File: LICENSE
Classifier: Development Status :: 4 - Beta
Classifier: License :: OSI Approved :: MIT License
Classifier: Operating System :: OS Independent
Classifier: Programming Language :: Python
Classifier: Programming Language :: Python :: 3
Classifier: Programming Language :: Python :: 3.13
Classifier: Topic :: Scientific/Engineering :: Artificial Intelligence
Classifier: Topic :: Software Development :: Libraries :: Python Modules
Classifier: Topic :: System :: Networking
Requires-Python: >=3.13
Requires-Dist: fastmcp>=2.9.0
Requires-Dist: ipinfo>=5.1.1
Requires-Dist: pydantic>=2.10.6
